{
    "totalscore" : " GESAMTERGEBNIS ",
    "singlescore1" : "Reinigung",
    "singlescore2" : "Persönliche Betreuung",
    "singlescore3" : "Komfort Zimmer",
    "singlescore4" : "Lage",
    "singlescore5" : "Hotelausstattung",
    "singlescore6" : "Frühstück",
    
    "alt1" : "Symbol Reinigung",
    "alt2" : "Icon Personal Care",
    "alt3" : "Comfort Symbol",
    "alt4" : "icon Standort",
    "alt5" : "Einrichtungen Symbol",
    "alt6" : "Frühstück Symbol",
    "alt7" : "Hauptbild Bewertungen"
}